aiogram_test_framework/__init__.py
aiogram_test_framework/base.py
aiogram_test_framework/client.py
aiogram_test_framework/factories.py
aiogram_test_framework/mock_bot.py
aiogram_test_framework/py.typed
aiogram_test_framework/request_capture.py
aiogram_test_framework/setup.py
aiogram_test_framework/types.py
aiogram_test_framework/user.py
aiogram_test_framework-1.0.3.dist-info/licenses/LICENSE
aiogram_test_framework-1.0.3.dist-info/METADATA
aiogram_test_framework-1.0.3.dist-info/WHEEL
aiogram_test_framework-1.0.3.dist-info/top_level.txt
aiogram_test_framework-1.0.3.dist-info/RECORD
