Metadata-Version: 2.4
Name: aiogram-test-framework
Version: 1.0.3
Summary: A testing framework for Aiogram 3.x Telegram bots
Author-email: Serhiy Gavka <sgavka@gmail.com>
License: MIT
Project-URL: Homepage, https://github.com/sgavka/aiogram-test-framework
Project-URL: Repository, https://github.com/sgavka/aiogram-test-framework
Project-URL: Issues, https://github.com/sgavka/aiogram-test-framework/issues
Keywords: aiogram,telegram,bot,testing,test-framework,mock
Classifier: Development Status :: 4 - Beta
Classifier: Intended Audience :: Developers
Classifier: License :: OSI Approved :: MIT License
Classifier: Operating System :: OS Independent
Classifier: Programming Language :: Python :: 3
Classifier: Programming Language :: Python :: 3.10
Classifier: Programming Language :: Python :: 3.11
Classifier: Programming Language :: Python :: 3.12
Classifier: Programming Language :: Python :: 3.13
Classifier: Framework :: AsyncIO
Classifier: Topic :: Software Development :: Testing
Classifier: Topic :: Software Development :: Testing :: Mocking
Classifier: Typing :: Typed
Requires-Python: >=3.10
License-File: LICENSE
Requires-Dist: aiogram>=3.4.0
Provides-Extra: dev
Requires-Dist: pytest>=7.0.0; extra == "dev"
Requires-Dist: pytest-asyncio>=0.21.0; extra == "dev"
Requires-Dist: pytest-cov>=4.0.0; extra == "dev"
Dynamic: license-file
